{"geocode_lodgeArea":[{"idx":"0","address":"제주 제주시 관덕로8길 24","lat":"33.5111012","long":"126.5230764"},{"idx":"1","address":"제주 제주시 애월읍 일주서로 6158","lat":"33.4592769","long":"126.3124259"},{"idx":"2","address":"제주 서귀포시 중정로 24-7 1층","lat":"33.2472587","long":"126.5590865"},{"idx":"3","address":"제주 서귀포시 동문동로 13-1 미도호스텔 게스트하우스","lat":"33.2500219","long":"126.5664606"},{"idx":"4","address":"제주 서귀포시 안덕면 사계북로41번길 30","lat":"33.2359906","long":"126.2954387"},{"idx":"5","address":"제주 제주시 제주대학로 77","lat":"33.4580218","long":"126.5601372"},{"idx":"6","address":"제주 제주시 한북로 338","lat":"33.4599739","long":"126.5376801"},{"idx":"7","address":"제주 제주시 조천읍 선진안길 21","lat":"33.4576112","long":"126.7044127"},{"idx":"8","address":"제주 제주시 우도면 우도로 225 1층 초원게스트하우스&카페","lat":"33.5117914","long":"126.9520179"},{"idx":"9","address":"제주 서귀포시 성산읍 성산중앙로 43","lat":"33.4636892","long":"126.933465"},{"idx":"10","address":"제주 서귀포시 성산읍 한도로 120","lat":"33.4685469","long":"126.9207208"},{"idx":"11","address":"제주 제주시 구좌읍 세화11길 18","lat":"33.52218149999999","long":"126.8610231"},{"idx":"12","address":"제주 제주시 한림읍 협재6길 22-4","lat":"33.3934582","long":"126.2422422"},{"idx":"13","address":"제주 제주시 한림읍 협재1길 27 1층 동행in협재","lat":"33.3976864","long":"126.2432576"},{"idx":"14","address":"제주 제주시 한림읍 명랑남길 17","lat":"33.4151161","long":"126.2712032"},{"idx":"15","address":"제주 제주시 애월읍 애월로2길 7 1층 오누게스트하우스","lat":"33.4628613","long":"126.3141409"},{"idx":"16","address":"제주 제주시 애월읍 애월로4길 18","lat":"33.4633064","long":"126.3141248"},{"idx":"17","address":"제주 제주시 조천읍 함덕29길 25-4 꼬르동게스트하우스","lat":"33.5423435","long":"126.6741398"},{"idx":"18","address":"제주 제주시 조천읍 함덕14길 28-2","lat":"33.5398799","long":"126.6650346"},{"idx":"19","address":"제주 제주시 조천읍 함덕서4길 60-21","lat":"33.5394501","long":"126.6664796"},{"idx":"20","address":"제주 제주시 조천읍 함덕30길 20-13","lat":"33.5380939","long":"126.6771778"},{"idx":"21","address":"제주 제주시 조천읍 조함해안로 356","lat":"33.5440366","long":"126.6537771"}]}